clickpoints/Addon.py
clickpoints/ClickPointsBooster.py
clickpoints/ConfigClickPoints_TEMPLATE.txt
clickpoints/Core.py
clickpoints/DataFile.py
clickpoints/SplashScreen.py
clickpoints/__clickpoints_addon__.txt
clickpoints/__init__.py
clickpoints/addons/CellDetector/CellDetector.py
clickpoints/addons/CellDetector/CellDetector.txt
clickpoints/addons/CellDetector/Desc.html
clickpoints/addons/CellDetector/Image.png
clickpoints/addons/CellMeasure/CellMeasure.py
clickpoints/addons/CellMeasure/CellMeasure.txt
clickpoints/addons/CellMeasure/Desc.html
clickpoints/addons/CellMeasure/Image.png
clickpoints/addons/DetectorTester/Desc.html
clickpoints/addons/DetectorTester/DetectorTester.py
clickpoints/addons/DetectorTester/DetectorTester.txt
clickpoints/addons/DetectorTester/SampleDetectors.py
clickpoints/addons/DistanceMeasurement/Desc.html
clickpoints/addons/DistanceMeasurement/DistanceMeasurement.py
clickpoints/addons/DistanceMeasurement/DistanceMeasurement.txt
clickpoints/addons/DistanceMeasurement/Image.png
clickpoints/addons/DistanceMeasurement/camera.json
clickpoints/addons/DriftCorrection/Desc.html
clickpoints/addons/DriftCorrection/DriftCorrection.py
clickpoints/addons/DriftCorrection/DriftCorrection.txt
clickpoints/addons/DriftCorrection/Image.png
clickpoints/addons/Dronpa/Data.txt
clickpoints/addons/Dronpa/Desc.html
clickpoints/addons/Dronpa/Dronpa.py
clickpoints/addons/Dronpa/FitDiffusionConstants.py
clickpoints/addons/Dronpa/GetIntensities.py
clickpoints/addons/Dronpa/Image.png
clickpoints/addons/Dronpa/TheanoExpm.py
clickpoints/addons/ExportForFlow/Data.txt
clickpoints/addons/ExportForFlow/Desc.html
clickpoints/addons/ExportForFlow/Export.py
clickpoints/addons/ExportToExcel/Data.txt
clickpoints/addons/ExportToExcel/Desc.html
clickpoints/addons/ExportToExcel/ExportToExcel.py
clickpoints/addons/ExportToExcel/Image.png
clickpoints/addons/FineContrastAdjust/Data.txt
clickpoints/addons/FineContrastAdjust/Desc.html
clickpoints/addons/FineContrastAdjust/FineContrast.py
clickpoints-1.10.0.dist-info/entry_points.txt
clickpoints-1.10.0.dist-info/LICENSE
clickpoints-1.10.0.dist-info/WHEEL
clickpoints-1.10.0.dist-info/METADATA
clickpoints-1.10.0.dist-info/RECORD
