Metadata-Version: 2.1
Name: clickpoints
Version: 1.10.0
Summary: Scientific toolbox for manual and automatic image evaluation.
Home-page: https://github.com/fabrylab/clickpoints
License: GPLv3
Author: Richard Gerum
Author-email: richard.gerum@fau.de
Maintainer: Alexander Winterl
Maintainer-email: alexander.winterl@fau.de
Requires-Python: >=3.8,<4.0
Classifier: License :: Other/Proprietary License
Classifier: Programming Language :: Python :: 3
Classifier: Programming Language :: Python :: 3.8
Classifier: Programming Language :: Python :: 3.9
Classifier: Programming Language :: Python :: 3.10
Classifier: Programming Language :: Python :: 3.11
Provides-Extra: docs
Requires-Dist: Pillow
Requires-Dist: PyQt5
Requires-Dist: QtAwesome
Requires-Dist: QtPy
Requires-Dist: imagecodecs
Requires-Dist: imageio (>=2.0.1)
Requires-Dist: imageio-ffmpeg
Requires-Dist: matplotlib
Requires-Dist: mock (>=4.0.3,<5.0.0); extra == "docs"
Requires-Dist: natsort
Requires-Dist: nbsphinx (>=0.8.9,<0.9.0); extra == "docs"
Requires-Dist: peewee (>=3.1)
Requires-Dist: psutil
Requires-Dist: python-dateutil (>=2.8.1)
Requires-Dist: qasync
Requires-Dist: qimage2ndarray
Requires-Dist: scikit-image (>=0.14)
Requires-Dist: scipy (==1.9.3)
Requires-Dist: sortedcontainers
Requires-Dist: sphinx-rtd-theme (>=1.1.1,<2.0.0); extra == "docs"
Requires-Dist: sphinxcontrib-bibtex (>=2.5.0,<3.0.0); extra == "docs"
Requires-Dist: sphinxcontrib-svg2pdfconverter (>=1.2.1,<2.0.0); extra == "docs"
Requires-Dist: tifffile (>=2020.2.16)
Project-URL: Documentation, https://clickpoints.readthedocs.io/
Project-URL: Repository, https://github.com/fabrylab/clickpoints
